setup.cfg
setup.py
naive_bayes.egg-info/PKG-INFO
naive_bayes.egg-info/SOURCES.txt
naive_bayes.egg-info/dependency_links.txt
naive_bayes.egg-info/requires.txt
naive_bayes.egg-info/top_level.txt
naivebayes/__init__.py