Metadata-Version: 1.0
Name: naive-bayes
Version: 0.1.1
Summary: Naive Bayes Text Classification
Home-page: UNKNOWN
Author: Yurii Shevchuk
Author-email: mail@itdxer.com
License: UNKNOWN
Keywords: naive bayes text classification classifier
Platform: UNKNOWN
